sgm3/__init__.py
sgm3/dialog.py
sgm3-0.1.1.dist-info/licenses/LICENSE.txt
sgm3-0.1.1.dist-info/METADATA
sgm3-0.1.1.dist-info/WHEEL
sgm3-0.1.1.dist-info/top_level.txt
sgm3-0.1.1.dist-info/RECORD
