Metadata-Version: 2.4
Name: sgm3
Version: 0.1.1
Summary: A user-friendly GUI module, made for Python 3.
Author: Swaraaj Arora
License-Expression: MIT
Requires-Python: >=3.10
License-File: LICENSE.txt
Dynamic: license-file
